kdp_api/__init__.py
kdp_api/api_client.py
kdp_api/api_response.py
kdp_api/configuration.py
kdp_api/exceptions.py
kdp_api/py.typed
kdp_api/rest.py
kdp_api/api/__init__.py
kdp_api/api/applications_api.py
kdp_api/api/attribute_based_access_control_api.py
kdp_api/api/authenticate_api.py
kdp_api/api/dataset_pairing_api.py
kdp_api/api/dataset_permissions_api.py
kdp_api/api/datasets_api.py
kdp_api/api/indexing_api.py
kdp_api/api/manage_records_api.py
kdp_api/api/read_and_query_api.py
kdp_api/api/users_and_groups_api.py
kdp_api/api/workspaces_api.py
kdp_api/api/write_api.py
kdp_api/models/__init__.py
kdp_api/models/abac_label_parser_paginator.py
kdp_api/models/abac_label_parsers.py
kdp_api/models/access_control_label.py
kdp_api/models/api_error.py
kdp_api/models/api_key.py
kdp_api/models/api_key_create_request.py
kdp_api/models/api_key_paginator.py
kdp_api/models/api_key_patch_request.py
kdp_api/models/api_key_response.py
kdp_api/models/application.py
kdp_api/models/application_create_request.py
kdp_api/models/application_create_request_required_dataset_access_inner.py
kdp_api/models/application_paginator.py
kdp_api/models/application_patch_request.py
kdp_api/models/application_required_dataset_access_inner.py
kdp_api/models/attribute.py
kdp_api/models/attribute_assignment.py
kdp_api/models/attribute_assignment_create_request.py
kdp_api/models/attribute_assignment_paginator.py
kdp_api/models/attribute_assignment_patch_request.py
kdp_api/models/attribute_create_request.py
kdp_api/models/attribute_paginator.py
kdp_api/models/attribute_patch_request.py
kdp_api/models/audit_log_configuration.py
kdp_api/models/audit_log_configuration_paginator.py
kdp_api/models/audit_log_event.py
kdp_api/models/audit_log_paginator.py
kdp_api/models/authentication.py
kdp_api/models/authentication_api_key.py
kdp_api/models/authentication_details.py
kdp_api/models/authentication_details_authentication.py
kdp_api/models/authentication_details_authentication_payload.py
kdp_api_python_client-4.177.0.dist-info/METADATA
kdp_api_python_client-4.177.0.dist-info/WHEEL
kdp_api_python_client-4.177.0.dist-info/top_level.txt
kdp_api_python_client-4.177.0.dist-info/RECORD
